spaw/__init__.py
spaw-0.2.dist-info/METADATA
spaw-0.2.dist-info/RECORD
spaw-0.2.dist-info/WHEEL
spaw-0.2.dist-info/top_level.txt
