Metadata-Version: 2.1
Name: spaw
Version: 0.2
Summary: SPAW is an Unofficial Streamable API Wrapper for Python
Home-page: https://github.com/amohamed11/StreamablePythonAPIWrapper
Author: Anas Mohamed
Author-email: amohamed@ualberta.ca
License: UNKNOWN
Platform: UNKNOWN
Classifier: Programming Language :: Python :: 3
Classifier: License :: OSI Approved :: MIT License
Classifier: Operating System :: OS Independent
